cosmos1/__init__.py
cosmos1/models/POST_TRAINING.md
cosmos1/models/__init__.py
cosmos1/models/autoregressive/README.md
cosmos1/models/autoregressive/__init__.py
cosmos1/models/autoregressive/model.py
cosmos1/models/autoregressive/assets/nemo/finetuned_result.mp4
cosmos1/models/autoregressive/assets/v1p0/input.jpg
cosmos1/models/autoregressive/assets/v1p0/input.mp4
cosmos1/models/autoregressive/assets/v1p0/output_from_image_input_12b.mp4
cosmos1/models/autoregressive/assets/v1p0/output_from_image_input_13b.mp4
cosmos1/models/autoregressive/assets/v1p0/output_from_video_input_12b.mp4
cosmos1/models/autoregressive/assets/v1p0/output_from_video_input_13b.mp4
cosmos1/models/autoregressive/assets/v1p0/batch_inputs/0.mp4
cosmos1/models/autoregressive/assets/v1p0/batch_inputs/1.mp4
cosmos1/models/autoregressive/assets/v1p0/batch_inputs/2.mp4
cosmos1/models/autoregressive/assets/v1p0/batch_inputs/3.mp4
cosmos1/models/autoregressive/assets/v1p0/batch_inputs/4.mp4
cosmos1/models/autoregressive/assets/v1p0/batch_inputs/5.mp4
cosmos1/models/autoregressive/assets/v1p0/batch_inputs/6.mp4
cosmos1/models/autoregressive/assets/v1p0/batch_inputs/7.mp4
cosmos1/models/autoregressive/assets/v1p0/batch_inputs/8.mp4
cosmos1/models/autoregressive/assets/v1p0/batch_inputs/9.mp4
cosmos1/models/autoregressive/assets/v1p0/batch_inputs/base.jsonl
cosmos1/models/autoregressive/assets/v1p0/batch_inputs/video2world.jsonl
cosmos1/models/autoregressive/configs/__init__.py
cosmos1/models/autoregressive/configs/base/__init__.py
cosmos1/models/autoregressive/configs/base/model.py
cosmos1/models/autoregressive/configs/base/model_config.py
cosmos1/models/autoregressive/configs/base/tokenizer.py
cosmos1/models/autoregressive/configs/inference/inference_config.py
cosmos1/models/autoregressive/diffusion_decoder/__init__.py
cosmos1/models/autoregressive/diffusion_decoder/inference.py
cosmos1/models/autoregressive/diffusion_decoder/model.py
cosmos1/models/autoregressive/diffusion_decoder/network.py
nvidia_cosmos-1.0.5.dist-info/LICENSE
nvidia_cosmos-1.0.5.dist-info/METADATA
nvidia_cosmos-1.0.5.dist-info/WHEEL
nvidia_cosmos-1.0.5.dist-info/top_level.txt
nvidia_cosmos-1.0.5.dist-info/RECORD
