Metadata-Version: 2.2
Name: nvidia-cosmos
Version: 1.0.5
Summary: Cosmos World Foundation Model
Author: NVIDIA Corporation
License: Apache-2.0
Project-URL: homepage, https://github.com/NVIDIA/Cosmos/
Project-URL: issues, https://github.com/NVIDIA/Cosmos/issues
Requires-Python: >=3.10
License-File: LICENSE
Requires-Dist: av
Requires-Dist: better-profanity
Requires-Dist: einops==0.7.0
Requires-Dist: einx==0.1.3
Requires-Dist: huggingface-hub>=0.26.2
Requires-Dist: hydra-core
Requires-Dist: imageio[ffmpeg]
Requires-Dist: iopath
Requires-Dist: loguru
Requires-Dist: mediapy
Requires-Dist: nltk
Requires-Dist: peft
Requires-Dist: pillow
Requires-Dist: retinaface-py
Requires-Dist: sentencepiece
Requires-Dist: termcolor
Requires-Dist: transformers==4.48.0
